accessible_graphs_pkg/__init__.py
accessible_graphs-0.0.4.dist-info/METADATA
accessible_graphs-0.0.4.dist-info/WHEEL
accessible_graphs-0.0.4.dist-info/license
accessible_graphs-0.0.4.dist-info/top_level.txt
accessible_graphs-0.0.4.dist-info/RECORD
