Metadata-Version: 2.1
Name: accessible-graphs
Version: 0.0.4
Summary: A package to make specific types of graphs accessible to low vision and blind users
Home-page: https://github.com/hasadna/accessible-graphs
Author: Mohammad Suliman
Author-email: mohmad.s93@gmail.com
License: UNKNOWN
Platform: UNKNOWN
Classifier: Programming Language :: Python :: 3
Classifier: License :: OSI Approved :: Apache Software License
Classifier: Operating System :: OS Independent
Requires-Python: >=3.6
